haupt/__init__.py
haupt/__main__.py
haupt/main.py
haupt/manage.py
haupt/pkg.py
haupt/py.typed
haupt/settings.py
haupt/apis/__init__.py
haupt/apis/apps.py
haupt/apis/patterns.py
haupt/apis/agents/__init__.py
haupt/apis/agents/urls.py
haupt/apis/agents/views.py
haupt/apis/bookmarks/__init__.py
haupt/apis/bookmarks/views.py
haupt/apis/endpoints/__init__.py
haupt/apis/endpoints/project.py
haupt/apis/endpoints/run.py
haupt/apis/methods/__init__.py
haupt/apis/methods/entity_stages.py
haupt/apis/methods/project_resources.py
haupt/apis/methods/run_lineage.py
haupt/apis/methods/runs.py
haupt/apis/project_resources/__init__.py
haupt/apis/project_resources/urls.py
haupt/apis/project_resources/views/__init__.py
haupt/apis/project_resources/views/runs.py
haupt/apis/project_resources/views/versions.py
haupt/apis/projects/__init__.py
haupt/apis/projects/urls.py
haupt/apis/projects/views.py
haupt/apis/run_lineage/__init__.py
haupt/apis/run_lineage/urls.py
haupt/apis/run_lineage/views.py
haupt/apis/runs/__init__.py
haupt/apis/runs/urls.py
haupt/apis/runs/views.py
haupt/apis/serializers/__init__.py
haupt/apis/serializers/artifacts.py
haupt/apis/serializers/project_stats.py
haupt/apis/serializers/project_versions.py
haupt/apis/serializers/projects.py
haupt/apis/serializers/runs.py
haupt/apis/serializers/base/__init__.py
haupt/apis/serializers/base/bookmarks_mixin.py
haupt/apis/serializers/base/cloning.py
haupt/apis/serializers/base/is_managed.py
haupt/apis/serializers/base/names.py
haupt/apis/serializers/base/owner_mixin.py
haupt/apis/serializers/base/pipeline.py
haupt/apis/serializers/base/project.py
haupt/apis/serializers/base/resources_mixin.py
haupt/apis/serializers/base/settings.py
haupt/apis/serializers/base/tags.py
haupt/apis/serializers/base/user_mixin.py
haupt/apis/serializers/base/uuid_slug_related_field.py
haupt/apis/versions/__init__.py
haupt/apis/versions/urls.py
haupt/apis/versions/views.py
haupt/background/__init__.py
haupt/background/celeryp/__init__.py
haupt-2.12.0.dist-info/licenses/LICENSE
haupt-2.12.0.dist-info/METADATA
haupt-2.12.0.dist-info/WHEEL
haupt-2.12.0.dist-info/entry_points.txt
haupt-2.12.0.dist-info/top_level.txt
haupt-2.12.0.dist-info/RECORD
