Metadata-Version: 2.4
Name: haupt
Version: 2.12.0
Summary: Lineage metadata API, artifacts streams, sandbox, ML-API, and spaces for Polyaxon.
Home-page: https://github.com/polyaxon/haupt
Author: Polyaxon, Inc.
Author-email: contact@polyaxon.com
Maintainer: Polyaxon, Inc.
Maintainer-email: contact@polyaxon.com
License: AGPLv3
Keywords: polyaxon,aws,s3,microsoft,azure,google cloud storage,gcs,deep-learning,machine-learning,data-science,neural-networks,artificial-intelligence,ai,reinforcement-learning,kubernetes,aws,microsoft,azure,google cloud,tensorFlow,pytorch,paddlepaddle,matplotlib,plotly,visualization,analytics,hyperopt,scikit-learn,optimization,bayesian-optimization
Platform: any
Classifier: Intended Audience :: Information Technology
Classifier: Intended Audience :: System Administrators
Classifier: Intended Audience :: Developers
Classifier: Intended Audience :: Science/Research
Classifier: Operating System :: OS Independent
Classifier: Programming Language :: Python :: 3
Classifier: Programming Language :: Python
Classifier: Topic :: Software Development :: Libraries :: Application Frameworks
Classifier: Topic :: Software Development :: Libraries :: Python Modules
Classifier: Topic :: Software Development :: Libraries
Classifier: Topic :: Software Development
Classifier: Topic :: Scientific/Engineering :: Artificial Intelligence
Classifier: Typing :: Typed
Classifier: Programming Language :: Python :: 3 :: Only
Classifier: Programming Language :: Python :: 3.6
Classifier: Programming Language :: Python :: 3.7
Classifier: Programming Language :: Python :: 3.8
Classifier: Programming Language :: Python :: 3.9
Classifier: Programming Language :: Python :: 3.10
Classifier: Programming Language :: Python :: 3.11
Requires-Python: >=3.9
License-File: LICENSE
Requires-Dist: Django<5.3
Requires-Dist: djangorestframework<3.17
Requires-Dist: django-cors-headers<4.10
Requires-Dist: numpy
Requires-Dist: polyaxon==2.12.*
Requires-Dist: traceml==1.2.*
Requires-Dist: hypertune==1.2.*
Provides-Extra: platform
Requires-Dist: celery==5.5.3; extra == "platform"
Requires-Dist: psycopg==3.2.12; extra == "platform"
Requires-Dist: psycopg-binary==3.2.12; extra == "platform"
Requires-Dist: redis==7.0.1; extra == "platform"
Provides-Extra: sandbox
Requires-Dist: whitenoise<=6.11.0; extra == "sandbox"
Requires-Dist: fsspec==2025.10.0; extra == "sandbox"
Requires-Dist: uvicorn[standard]<0.39; extra == "sandbox"
Requires-Dist: uvloop==0.22.1; extra == "sandbox"
Requires-Dist: aiofiles<=25.1.0; extra == "sandbox"
Requires-Dist: kubernetes_asyncio>=28.2.1; extra == "sandbox"
Requires-Dist: nbconvert>=6.5.0; extra == "sandbox"
Requires-Dist: pandas<=2.2.3; extra == "sandbox"
Requires-Dist: pyarrow<22.1; extra == "sandbox"
Provides-Extra: fs
Requires-Dist: adlfs==2025.8.0; extra == "fs"
Requires-Dist: fsspec==2025.10.0; extra == "fs"
Requires-Dist: gcsfs==2025.10.0; extra == "fs"
Requires-Dist: s3fs==2025.10.0; extra == "fs"
Provides-Extra: streams
Requires-Dist: fsspec==2025.10.0; extra == "streams"
Requires-Dist: uvicorn[standard]<0.39; extra == "streams"
Requires-Dist: uvloop==0.22.1; extra == "streams"
Requires-Dist: aiofiles<=25.1.0; extra == "streams"
Requires-Dist: kubernetes_asyncio>=28.2.1; extra == "streams"
Requires-Dist: nbconvert>=6.5.0; extra == "streams"
Requires-Dist: pandas<=2.2.3; extra == "streams"
Requires-Dist: pyarrow<22.1; extra == "streams"
Provides-Extra: dev
Requires-Dist: django-debug-toolbar; extra == "dev"
Requires-Dist: pandas; extra == "dev"
Requires-Dist: ipython; extra == "dev"
Dynamic: author
Dynamic: author-email
Dynamic: classifier
Dynamic: description
Dynamic: description-content-type
Dynamic: home-page
Dynamic: keywords
Dynamic: license
Dynamic: license-file
Dynamic: maintainer
Dynamic: maintainer-email
Dynamic: platform
Dynamic: provides-extra
Dynamic: requires-dist
Dynamic: requires-python
Dynamic: summary
